ProcessedPiRecorder/Buffer.py
ProcessedPiRecorder/Latency.py
ProcessedPiRecorder/ProcessedPiRecorder.py
ProcessedPiRecorder/QueueHandler.py
ProcessedPiRecorder/__init__.py
ProcessedPiRecorder-0.3.1.dist-info/LICENSE
ProcessedPiRecorder-0.3.1.dist-info/METADATA
ProcessedPiRecorder-0.3.1.dist-info/WHEEL
ProcessedPiRecorder-0.3.1.dist-info/top_level.txt
ProcessedPiRecorder-0.3.1.dist-info/RECORD
