Metadata-Version: 2.1
Name: ProcessedPiRecorder
Version: 0.3.1
Summary: Multiprocessed picamera class for simpler and faster computer vision
Home-page: https://github.com/mattisabrat/ProcessedPiRecorder
Author: Matthew Davenport
Author-email: mdavenport@rockefeller.edu
License: GPLv3
Platform: UNKNOWN
Classifier: Development Status :: 3 - Alpha
Classifier: License :: OSI Approved :: GNU General Public License v3 (GPLv3)
Classifier: Programming Language :: Python :: 3 :: Only
Classifier: Operating System :: POSIX :: Linux
Requires-Dist: picamera (==1.13)
Requires-Dist: opencv-contrib-python (==3.4.4.19)
Requires-Dist: tifffile (==2019.7.26)
Requires-Dist: numpy (==1.17.0)
Requires-Dist: imageio (==2.6.1)
